gsm0338/__init__.py
gsm0338/charset.py
gsm0338/codec.py
gsm0338/unicode.py
gsm0338-1.0.0.dist-info/DESCRIPTION.rst
gsm0338-1.0.0.dist-info/METADATA
gsm0338-1.0.0.dist-info/RECORD
gsm0338-1.0.0.dist-info/WHEEL
gsm0338-1.0.0.dist-info/metadata.json
gsm0338-1.0.0.dist-info/top_level.txt
test/__init__.py
test/test_charset.py
test/test_codec.py
test/test_errors.py
test/test_register.py
